pglogicalmanager/__init__.py
pglogicalmanager/__main__.py
pglogicalmanager/manager.py
pglogicalmanager/__pycache__/__init__.cpython-37.pyc
pglogicalmanager/__pycache__/__main__.cpython-37.pyc
pglogicalmanager/__pycache__/manager.cpython-37.pyc
pg_logical_manager-0.4.3.dist-info/LICENSE
pg_logical_manager-0.4.3.dist-info/METADATA
pg_logical_manager-0.4.3.dist-info/WHEEL
pg_logical_manager-0.4.3.dist-info/entry_points.txt
pg_logical_manager-0.4.3.dist-info/top_level.txt
pg_logical_manager-0.4.3.dist-info/RECORD
