Metadata-Version: 2.1
Name: pg-logical-manager
Version: 0.4.3
Summary: View and manage logical subscriptions for a PostgreSQL cluster.
Home-page: https://github.com/levkk/pg-logical-manager
Author: Lev Kokotov
Author-email: lev.kokotov@instacart.com
License: UNKNOWN
Platform: UNKNOWN
Classifier: Programming Language :: Python :: 3.6
Classifier: Programming Language :: Python :: 3.7
Classifier: Programming Language :: Python :: 3.8
Classifier: License :: OSI Approved :: MIT License
Classifier: Operating System :: OS Independent
Requires-Python: >=3.6
Requires-Dist: Click (>=7.0)
Requires-Dist: colorama (>=0.4.3)
Requires-Dist: prettytable (>=0.7.2)
Requires-Dist: psycopg2 (>=2.8.4)
Requires-Dist: python-dotenv (>=0.10.3)
Provides-Extra: dev
Requires-Dist: pytest ; extra == 'dev'
